[{"place_id": 137921102, "licence": "Data \u00a9 OpenStreetMap contributors, ODbL 1.0. http://osm.org/copyright", "osm_type": "node", "osm_id": 289445435, "lat": "52.3294483", "lon": "4.9305189", "class": "railway", "type": "station", "place_rank": 30, "importance": 0.3100379589897483, "addresstype": "railway", "name": "Van der Madeweg", "display_name": "Van der Madeweg, Amstel Business Park, Amsterdam-Duivendrecht, Ouder-Amstel, Noord-Holland, Nederland, 1114 AK, Nederland", "boundingbox": ["52.3244483", "52.3344483", "4.9255189", "4.9355189"]}, {"place_id": 138070242, "licence": "Data \u00a9 OpenStreetMap contributors, ODbL 1.0. http://osm.org/copyright", "osm_type": "way", "osm_id": 761458311, "lat": "52.3289396", "lon": "4.9305151", "class": "highway", "type": "secondary", "place_rank": 26, "importance": 0.1580839831692664, "addresstype": "road", "name": "Van der Madeweg", "display_name": "Van der Madeweg, Amstel Business Park, Amsterdam-Duivendrecht, Ouder-Amstel, Noord-Holland, Nederland, 1114 AK, Nederland", "boundingbox": ["52.3286617", "52.3291080", "4.9297095", "4.9309608"]}, {"place_id": 137919567, "licence": "Data \u00a9 OpenStreetMap contributors, ODbL 1.0. http://osm.org/copyright", "osm_type": "way", "osm_id": 761458317, "lat": "52.3262744", "lon": "4.9230777", "class": "highway", "type": "secondary", "place_rank": 26, "importance": 0.1580839831692664, "addresstype": "road", "name": "Van der Madeweg", "display_name": "Van der Madeweg, Amstel Business Park, Amsterdam-Duivendrecht, Ouder-Amstel, Noord-Holland, Nederland, 1114 AM, Nederland", "boundingbox": ["52.3251350", "52.3276197", "4.9197642", "4.9269975"]}, {"place_id": 138494268, "licence": "Data \u00a9 OpenStreetMap contributors, ODbL 1.0. http://osm.org/copyright", "osm_type": "way", "osm_id": 7046864, "lat": "52.328941", "lon": "4.9308361", "class": "highway", "type": "secondary", "place_rank": 26, "importance": 0.1580839831692664, "addresstype": "road", "name": "Van der Madeweg", "display_name": "Van der Madeweg, Amstel Business Park, Amsterdam-Duivendrecht, Ouder-Amstel, Noord-Holland, Nederland, 1115 EA, Nederland", "boundingbox": ["52.3286969", "52.3291755", "4.9301168", "4.9314855"]}, {"place_id": 138094216, "licence": "Data \u00a9 OpenStreetMap contributors, ODbL 1.0. http://osm.org/copyright", "osm_type": "way", "osm_id": 761458314, "lat": "52.3280017", "lon": "4.9281143", "class": "highway", "type": "secondary", "place_rank": 26, "importance": 0.1580839831692664, "addresstype": "road", "name": "Van der Madeweg", "display_name": "Van der Madeweg, Amstel Business Park, Amsterdam-Duivendrecht, Ouder-Amstel, Noord-Holland, Nederland, 1114 AE, Nederland", "boundingbox": ["52.3279319", "52.3284652", "4.9279451", "4.9294471"]}, {"place_id": 138351350, "licence": "Data \u00a9 OpenStreetMap contributors, ODbL 1.0. http://osm.org/copyright", "osm_type": "way", "osm_id": 761458312, "lat": "52.3291929", "lon": "4.9311972", "class": "highway", "type": "secondary", "place_rank": 26, "importance": 0.1580839831692664, "addresstype": "road", "name": "Van der Madeweg", "display_name": "Van der Madeweg, Amsterdam-Duivendrecht, Ouder-Amstel, Noord-Holland, Nederland, 1115 EA, Nederland", "boundingbox": ["52.3291080", "52.3292574", "4.9309608", "4.9314154"]}, {"place_id": 138093001, "licence": "Data \u00a9 OpenStreetMap contributors, ODbL 1.0. http://osm.org/copyright", "osm_type": "way", "osm_id": 1033449741, "lat": "52.3263659", "lon": "4.9229928", "class": "highway", "type": "unclassified", "place_rank": 26, "importance": 0.10000999999999993, "addresstype": "road", "name": "Van der Madeweg", "display_name": "Van der Madeweg, Amstel Business Park, Amsterdam-Duivendrecht, Ouder-Amstel, Noord-Holland, Nederland, 1114 AM, Nederland", "boundingbox": ["52.3263659", "52.3264388", "4.9229211", "4.9229928"]}, {"place_id": 138053719, "licence": "Data \u00a9 OpenStreetMap contributors, ODbL 1.0. http://osm.org/copyright", "osm_type": "way", "osm_id": 24343387, "lat": "52.3295821", "lon": "4.9370493", "class": "highway", "type": "secondary", "place_rank": 26, "importance": 0.10000999999999993, "addresstype": "road", "name": "Van der Madeweg", "display_name": "Van der Madeweg, Duivendrecht, Ouder-Amstel, Noord-Holland, Nederland, 1115 DK, Nederland", "boundingbox": ["52.3295050", "52.3295821", "4.9370493", "4.9376527"]}, {"place_id": 138068726, "licence": "Data \u00a9 OpenStreetMap contributors, ODbL 1.0. http://osm.org/copyright", "osm_type": "way", "osm_id": 738480801, "lat": "52.3243386", "lon": "4.9178495", "class": "highway", "type": "unclassified", "place_rank": 26, "importance": 0.10000999999999993, "addresstype": "road", "name": "Van der Madeweg", "display_name": "Van der Madeweg, Amstel Business Park, Amsterdam-Duivendrecht, Ouder-Amstel, Noord-Holland, Nederland, 1114 AN, Nederland", "boundingbox": ["52.3242254", "52.3245398", "4.9177233", "4.9180571"]}, {"place_id": 137921291, "licence": "Data \u00a9 OpenStreetMap contributors, ODbL 1.0. http://osm.org/copyright", "osm_type": "way", "osm_id": 7046874, "lat": "52.3296408", "lon": "4.9365086", "class": "highway", "type": "secondary", "place_rank": 26, "importance": 0.10000999999999993, "addresstype": "road", "name": "Van der Madeweg", "display_name": "Van der Madeweg, Duivendrecht, Ouder-Amstel, Noord-Holland, Nederland, 1115 DV, Nederland", "boundingbox": ["52.3295821", "52.3298334", "4.9348434", "4.9370493"]}]